{
  "annotations": {
    "list": []
  },
  "editable": true,
  "fiscalYearStartMonth": 0,
  "graphTooltip": 0,
  "id": null,
  "links": [],
  "panels": [
    {
      "title": "Orders Created (rate/min)",
      "type": "timeseries",
      "gridPos": { "h": 8, "w": 12, "x": 0, "y": 0 },
      "targets": [
        {
          "expr": "rate(orders_created_total[5m]) * 60",
          "legendFormat": "{{status}}"
        }
      ]
    },
    {
      "title": "Saga Duration (p50, p95, p99)",
      "type": "timeseries",
      "gridPos": { "h": 8, "w": 12, "x": 12, "y": 0 },
      "targets": [
        {
          "expr": "histogram_quantile(0.50, rate(saga_duration_seconds_bucket[5m]))",
          "legendFormat": "p50"
        },
        {
          "expr": "histogram_quantile(0.95, rate(saga_duration_seconds_bucket[5m]))",
          "legendFormat": "p95"
        },
        {
          "expr": "histogram_quantile(0.99, rate(saga_duration_seconds_bucket[5m]))",
          "legendFormat": "p99"
        }
      ]
    },
    {
      "title": "Saga Success Rate",
      "type": "gauge",
      "gridPos": { "h": 8, "w": 6, "x": 0, "y": 8 },
      "targets": [
        {
          "expr": "rate(saga_result_total{result=\"completed\"}[5m]) / rate(saga_result_total[5m]) * 100"
        }
      ],
      "fieldConfig": {
        "defaults": {
          "unit": "percent",
          "min": 0,
          "max": 100,
          "thresholds": {
            "steps": [
              { "color": "red", "value": 0 },
              { "color": "yellow", "value": 95 },
              { "color": "green", "value": 99 }
            ]
          }
        }
      }
    },
    {
      "title": "gRPC Request Duration (p99)",
      "type": "timeseries",
      "gridPos": { "h": 8, "w": 18, "x": 6, "y": 8 },
      "targets": [
        {
          "expr": "histogram_quantile(0.99, rate(grpc_request_duration_seconds_bucket[5m]))",
          "legendFormat": "{{method}}"
        }
      ]
    },
    {
      "title": "gRPC Error Rate",
      "type": "timeseries",
      "gridPos": { "h": 8, "w": 12, "x": 0, "y": 16 },
      "targets": [
        {
          "expr": "rate(grpc_requests_total{code!=\"OK\"}[5m]) / rate(grpc_requests_total[5m]) * 100",
          "legendFormat": "{{method}} - {{code}}"
        }
      ]
    },
    {
      "title": "Stock Reservations",
      "type": "timeseries",
      "gridPos": { "h": 8, "w": 12, "x": 12, "y": 16 },
      "targets": [
        {
          "expr": "rate(stock_reservations_total[5m]) * 60",
          "legendFormat": "{{result}}"
        }
      ]
    }
  ],
  "schemaVersion": 39,
  "tags": ["micromart"],
  "templating": { "list": [] },
  "time": { "from": "now-1h", "to": "now" },
  "title": "Micromart - Order Service",
  "uid": "micromart-orders"
}
